LICENSE.txt
README.md
setup.py
bin/fill-episode
bin/generate-nfo
bin/generate-show-nfo
bin/next-artwork
bin/next-episode
bin/next-season
bin/remove-episode
src/next_episode/__init__.py
src/next_episode/app.py
src/next_episode/artwork.py
src/next_episode/file_list.py
src/next_episode/show_nfo.py
src/next_episode/template.py
src/tvshow_manager.egg-info/PKG-INFO
src/tvshow_manager.egg-info/SOURCES.txt
src/tvshow_manager.egg-info/dependency_links.txt
src/tvshow_manager.egg-info/requires.txt
src/tvshow_manager.egg-info/top_level.txt