Metadata-Version: 2.1
Name: tvshow-manager
Version: 1.0.0
Summary: console commands to turn video folders into kodi importable tv seriesj
Home-page: https://github.com/svensp/next_episode
Author: Sven Speckmaier
License: MIT
Download-URL: https://github.com/svensp/next_episode/archive/refs/tags/1.0.0.tar.gz
Keywords: kodi
Platform: UNKNOWN
Classifier: Programming Language :: Python :: 3
Classifier: License :: OSI Approved :: MIT License
Classifier: Operating System :: OS Independent
License-File: LICENSE.txt
